dockermake
